datafiller/__init__.py
datafiller/_optimask.py
datafiller/datasets/__init__.py
datafiller/datasets/_datasets.py
datafiller/datasets/_misc.py
datafiller/estimators/__init__.py
datafiller/estimators/elm.py
datafiller/estimators/ridge.py
datafiller/multivariate/__init__.py
datafiller/multivariate/_numba_utils.py
datafiller/multivariate/_scoring.py
datafiller/multivariate/_utils.py
datafiller/multivariate/imputer.py
datafiller/timeseries/__init__.py
datafiller/timeseries/_utils.py
datafiller/timeseries/imputer.py
datafiller-0.2.1.dist-info/METADATA
datafiller-0.2.1.dist-info/WHEEL
datafiller-0.2.1.dist-info/licenses/LICENSE
datafiller-0.2.1.dist-info/RECORD
