Metadata-Version: 2.4
Name: datafiller
Version: 0.2.1
Summary: A python package for easy data imputation
Project-URL: Homepage, https://github.com/CyrilJl/datafiller
Project-URL: Documentation, https://datafiller.readthedocs.io
Author: Cyril Joly
License-File: LICENSE
Requires-Dist: numba
Requires-Dist: numpy
Requires-Dist: pandas
Requires-Dist: scikit-learn
Requires-Dist: tqdm
Provides-Extra: test
Requires-Dist: pooch; extra == 'test'
Requires-Dist: pytest; extra == 'test'
Requires-Dist: pytest-cov; extra == 'test'
